lightning_gpt/__about__.py
lightning_gpt/__init__.py
lightning_gpt/bench.py
lightning_gpt/callbacks.py
lightning_gpt/data.py
lightning_gpt/models.py
mingpt/__init__.py
mingpt/bpe.py
mingpt/model.py
mingpt/trainer.py
mingpt/utils.py
nanogpt/.git
nanogpt/.gitattributes
nanogpt/LICENSE
nanogpt/README.md
nanogpt/bench.py
nanogpt/configurator.py
nanogpt/model.py
nanogpt/sample.py
nanogpt/scaling_laws.ipynb
nanogpt/train.py
nanogpt/transformer_sizing.ipynb
nanogpt/assets/gpt2_124M_loss.png
nanogpt/assets/nanogpt.jpg
nanogpt/config/eval_gpt2.py
nanogpt/config/eval_gpt2_large.py
nanogpt/config/eval_gpt2_medium.py
nanogpt/config/eval_gpt2_xl.py
nanogpt/config/finetune_shakespeare.py
nanogpt/config/train_gpt2.py
nanogpt/config/train_shakespeare_char.py
nanogpt/data/openwebtext/prepare.py
nanogpt/data/openwebtext/readme.md
nanogpt/data/shakespeare/prepare.py
nanogpt/data/shakespeare/readme.md
nanogpt/data/shakespeare_char/prepare.py
nanogpt/data/shakespeare_char/readme.md
lightning_gpt-0.1.1.dist-info/LICENSE
lightning_gpt-0.1.1.dist-info/METADATA
lightning_gpt-0.1.1.dist-info/WHEEL
lightning_gpt-0.1.1.dist-info/top_level.txt
lightning_gpt-0.1.1.dist-info/RECORD
