Metadata-Version: 2.1
Name: lightning-gpt
Version: 0.1.1
Summary: GPT training in Lightning
Home-page: https://github.com/Lightning-AI/lightning-GPT
Download-URL: https://github.com/Lightning-AI/lightning-GPT/archive/main.zip
Author: Lightning-AI et al.
Author-email: luca@lightning.ai
License: Apache-2.0
Project-URL: Bug Tracker, https://github.com/Lightning-AI/lightning-GPT/issues
Project-URL: Documentation, https://github.com/Lightning-AI/lightning-GPT
Project-URL: Source Code, https://github.com/Lightning-AI/lightning-GPT
Keywords: deep learning,machine learning,pytorch,transformers,gpt,AI
Classifier: Environment :: Console
Classifier: Natural Language :: English
Classifier: Development Status :: 4 - Beta
Classifier: Intended Audience :: Developers
Classifier: Topic :: Scientific/Engineering :: Artificial Intelligence
Classifier: Topic :: Scientific/Engineering :: Information Analysis
Classifier: License :: OSI Approved :: Apache Software License
Classifier: Operating System :: OS Independent
Classifier: Programming Language :: Python :: 3
Classifier: Programming Language :: Python :: 3.8
Classifier: Programming Language :: Python :: 3.9
Classifier: Programming Language :: Python :: 3.10
Requires-Python: >=3.8
License-File: LICENSE
Requires-Dist: lightning[app] >=2.1.0
Requires-Dist: torch >=1.10.0
Requires-Dist: numpy
Provides-Extra: all
Requires-Dist: deepspeed >=0.6.0 ; extra == 'all'
Requires-Dist: tqdm ; extra == 'all'
Requires-Dist: tiktoken ; extra == 'all'
Requires-Dist: datasets ; extra == 'all'
Provides-Extra: deepspeed
Requires-Dist: deepspeed >=0.6.0 ; extra == 'deepspeed'
Provides-Extra: dev
Requires-Dist: deepspeed >=0.6.0 ; extra == 'dev'
Requires-Dist: tqdm ; extra == 'dev'
Requires-Dist: tiktoken ; extra == 'dev'
Requires-Dist: datasets ; extra == 'dev'
Requires-Dist: lightning >=1.8.4 ; extra == 'dev'
Requires-Dist: pytest-cov ==4.0.0 ; extra == 'dev'
Requires-Dist: codecov ==2.1.13 ; extra == 'dev'
Requires-Dist: coverage ==6.5.0 ; extra == 'dev'
Requires-Dist: pytest ==7.2.0 ; extra == 'dev'
Provides-Extra: nanogpt
Requires-Dist: tqdm ; extra == 'nanogpt'
Requires-Dist: tiktoken ; extra == 'nanogpt'
Requires-Dist: datasets ; extra == 'nanogpt'
Provides-Extra: test
Requires-Dist: lightning >=1.8.4 ; extra == 'test'
Requires-Dist: pytest-cov ==4.0.0 ; extra == 'test'
Requires-Dist: codecov ==2.1.13 ; extra == 'test'
Requires-Dist: coverage ==6.5.0 ; extra == 'test'
Requires-Dist: pytest ==7.2.0 ; extra == 'test'
